renogyapi/__init__.py
renogyapi/auth.py
renogyapi/exceptions.py
py_renogy-1.2.1.dist-info/LICENSE
py_renogy-1.2.1.dist-info/METADATA
py_renogy-1.2.1.dist-info/WHEEL
py_renogy-1.2.1.dist-info/top_level.txt
py_renogy-1.2.1.dist-info/RECORD
