Metadata-Version: 2.1
Name: py-renogy
Version: 1.2.1
Summary: Python wrapper for Renogy API
Home-page: https://github.com/firstof9/py-renogy
Author: firstof9
Author-email: firstof9@gmail.com
License: UNKNOWN
Download-URL: https://github.com/firstof9/py-renogy
Platform: UNKNOWN
Classifier: Development Status :: 4 - Beta
Classifier: Intended Audience :: Developers
Classifier: Natural Language :: English
Classifier: Programming Language :: Python :: 3
Classifier: Programming Language :: Python :: 3.12
Classifier: Programming Language :: Python :: 3.13
Requires-Python: >=3.10
License-File: LICENSE
Requires-Dist: aiohttp
